{
  "annotations": {
    "changelogDate": "20240707071032"
  },
  "applications": "*",
  "dto": "mapstruct",
  "fields": [
    {
      "fieldName": "entityClass",
      "fieldType": "String"
    },
    {
      "fieldName": "entityId",
      "fieldType": "Long"
    }
  ],
  "name": "ObjectiveCategoryElement",
  "relationships": [
    {
      "otherEntityName": "objectiveCategory",
      "otherEntityRelationshipName": "possibleValues",
      "relationshipName": "objectiveCategory",
      "relationshipSide": "right",
      "relationshipType": "many-to-one"
    }
  ],
  "searchEngine": "no",
  "service": "serviceImpl"
}
